LICENSE
README.md
setup.py
django_ministripe/__init__.py
django_ministripe/admin.py
django_ministripe/apps.py
django_ministripe/models.py
django_ministripe/receivers.py
django_ministripe/signals.py
django_ministripe/urls.py
django_ministripe/views.py
django_ministripe.egg-info/PKG-INFO
django_ministripe.egg-info/SOURCES.txt
django_ministripe.egg-info/dependency_links.txt
django_ministripe.egg-info/requires.txt
django_ministripe.egg-info/top_level.txt
django_ministripe/migrations/0001_initial.py
django_ministripe/migrations/__init__.py